pyenv_validator/__init__.py
pyenv_validator/pyenv_validator.py
pyenv_validator/version.py
pyenv_validator-0.2.0.dist-info/METADATA
pyenv_validator-0.2.0.dist-info/WHEEL
pyenv_validator-0.2.0.dist-info/top_level.txt
pyenv_validator-0.2.0.dist-info/RECORD
