Metadata-Version: 2.1
Name: pyenv-validator
Version: 0.2.0
Home-page: https://github.com/ombulabs/pyenv-validator
Author: OmbuLabs - The Lean Software Boutique LLC
Author-email: oss@ombulabs.com
Classifier: Programming Language :: Python :: 3.10
Classifier: License :: OSI Approved :: MIT License
Classifier: Operating System :: OS Independent
Requires-Python: >=3.10
